README.md
setup.cfg
setup.py
manager_cw_bot_api/__init__.py
manager_cw_bot_api/analytics.py
manager_cw_bot_api/business.py
manager_cw_bot_api/business_answers.py
manager_cw_bot_api/business_handler.py
manager_cw_bot_api/buttons.py
manager_cw_bot_api/create_table.py
manager_cw_bot_api/fsm_handler.py
manager_cw_bot_api/get_business_conn_and_info_conn.py
manager_cw_bot_api/giga_images.py
manager_cw_bot_api/giga_request.py
manager_cw_bot_api/gigachatai.py
manager_cw_bot_api/handler_db_sub_operations.py
manager_cw_bot_api/handler_email.py
manager_cw_bot_api/handler_email_sender.py
manager_cw_bot_api/handler_promo.py
manager_cw_bot_api/handler_successful_payment.py
manager_cw_bot_api/handler_yookassa.py
manager_cw_bot_api/mysql_connection.py
manager_cw_bot_api/pdf_generate_data.py
manager_cw_bot_api/refund.py
manager_cw_bot_api/send_invoice.py
manager_cw_bot_api/tests.py
manager_cw_bot_api/tickets.py
manager_cw_bot_api.egg-info/PKG-INFO
manager_cw_bot_api.egg-info/SOURCES.txt
manager_cw_bot_api.egg-info/dependency_links.txt
manager_cw_bot_api.egg-info/requires.txt
manager_cw_bot_api.egg-info/top_level.txt