Metadata-Version: 2.1
Name: manager_cw_bot_api
Version: 6.0.0
Summary: Python LIB for Business users in Telegram (For admin - business-person; Manager CW Bot API).
Home-page: https://github.com/cwr-su/manager_cw_bot_api
Download-URL: https://github.com/cwr-su/manager_cw_bot_api/archive/refs/heads/main.zip
Author: Alexander Laptev, CW
Author-email: cwr@cwr.su
License: Apache License, Version 2.0, see LICENSE file
Project-URL: Documentation, https://docs.cwr.su/
Classifier: License :: OSI Approved :: Apache Software License
Classifier: Operating System :: OS Independent
Classifier: Intended Audience :: End Users/Desktop
Classifier: Intended Audience :: Developers
Classifier: Programming Language :: Python
Classifier: Programming Language :: Python :: 3.9
Classifier: Programming Language :: Python :: 3.10
Classifier: Programming Language :: Python :: 3.11
Classifier: Programming Language :: Python :: 3.12
Classifier: Programming Language :: Python :: Implementation :: PyPy
Requires-Python: >=3.9
Requires-Dist: PyMySQL
Requires-Dist: aiogram
Requires-Dist: requests
Requires-Dist: yookassa
Requires-Dist: fpdf2
